elements.py
main.py
print.py
Periodic_Table_Info-0.3.0.dist-info/LICENSE.md
Periodic_Table_Info-0.3.0.dist-info/METADATA
Periodic_Table_Info-0.3.0.dist-info/WHEEL
Periodic_Table_Info-0.3.0.dist-info/entry_points.txt
Periodic_Table_Info-0.3.0.dist-info/top_level.txt
Periodic_Table_Info-0.3.0.dist-info/RECORD
