Metadata-Version: 2.1
Name: Periodic-Table-Info
Version: 0.3.0
Summary: Print all the elements in the Periodic Table of the Elements, with an interactive prompt to learn more.
Home-page: https://github.com/Dog-Face-Development/Periodic-Table-Info
Author: willtheorangeguy
License: # GNU GENERAL PUBLIC LICENSE        
Project-URL: Homepage, https://github.com/Dog-Face-Development/Periodic-Table-Info
Project-URL: Bug Tracker, https://github.com/Dog-Face-Development/Periodic-Table-Info/issues
Keywords: periodic table education info cli
Classifier: Development Status :: 3 - Alpha
Classifier: License :: OSI Approved :: GNU General Public License v3 (GPLv3)
Classifier: Natural Language :: English
Classifier: Operating System :: OS Independent
Classifier: Topic :: Education
Requires-Python: >=3.9
License-File: LICENSE.md
